kyuml/__init__.py
kyuml/models/__init__.py
kyuml/models/autogluon_trainable.py
kyuml/models/contrib/__init__.py
kyuml/models/contrib/big_model.py
kyuml/models/contrib/eureka_model.py
kyuml/models/contrib/tests/__init__.py
kyuml/utils/__init__.py
kyuml/utils/logic_converter.py
kyuml-2023.2.7.dist-info/LICENSE
kyuml-2023.2.7.dist-info/METADATA
kyuml-2023.2.7.dist-info/WHEEL
kyuml-2023.2.7.dist-info/top_level.txt
kyuml-2023.2.7.dist-info/RECORD
