Metadata-Version: 2.1
Name: kyuml
Version: 2023.2.7
Summary: Personal library
Home-page: https://github.com/kyu90/kyu_personal
Author: kyunam
Author-email: rbska56455@gmail.com
License: UNKNOWN
Platform: UNKNOWN
Classifier: Programming Language :: Python :: 3
Classifier: License :: OSI Approved :: MIT License
Classifier: Operating System :: OS Independent
Requires-Python: >=3.6
License-File: LICENSE
Requires-Dist: aiohttp[speedups]
Requires-Dist: autogluon.tabular (==0.2.0)
Requires-Dist: boto3
Requires-Dist: catboost (<0.25.0,>=0.24.3)
Requires-Dist: haversine (<2.4,>=2.3.1)
Requires-Dist: joblib
Requires-Dist: lightgbm (<2.4.0,>=2.3.1)
Requires-Dist: numpy (<1.20,>=1.19.2)
Requires-Dist: pandas (<1.2.0,>=1.1.1)
Requires-Dist: pytz
Requires-Dist: requests
Requires-Dist: scikit-learn (<0.24,>=0.23.2)
Requires-Dist: simplejson
Requires-Dist: torch (<1.9.0,>=1.8.1)
Requires-Dist: xgboost (<1.3,>=1.2.1)
Requires-Dist: ipyparallel (==8.2.1)
